LICENSE.txt
MANIFEST.in
README.rst
requirements-test.txt
setup.py
jsonrpc_requests/__init__.py
jsonrpc_requests/jsonrpc.py
jsonrpc_requests.egg-info/PKG-INFO
jsonrpc_requests.egg-info/SOURCES.txt
jsonrpc_requests.egg-info/dependency_links.txt
jsonrpc_requests.egg-info/requires.txt
jsonrpc_requests.egg-info/top_level.txt