Metadata-Version: 1.1
Name: jsonrpc-requests
Version: 0.3
Summary: A JSON-RPC client library, backed by requests
Home-page: http://github.com/gciotta/jsonrpc-requests
Author: Giuseppe Ciotta
Author-email: gciotta@gmail.com
License: BSD
Keywords: json-rpc requests
Platform: UNKNOWN
Classifier: Development Status :: 4 - Beta
Classifier: Intended Audience :: Developers
Classifier: Topic :: Software Development :: Libraries
Classifier: License :: OSI Approved :: BSD License
Classifier: Programming Language :: Python :: 2
Classifier: Programming Language :: Python :: 2.7
Classifier: Programming Language :: Python :: 3
Classifier: Programming Language :: Python :: 3.4
